README.rst
setup.cfg
setup.py
seizure/__init__.py
seizure/config.py
seizure/scripts.py
seizure.egg-info/PKG-INFO
seizure.egg-info/SOURCES.txt
seizure.egg-info/dependency_links.txt
seizure.egg-info/entry_points.txt
seizure.egg-info/requires.txt
seizure.egg-info/top_level.txt
seizure/lib/__init__.py
seizure/lib/conversion.py
seizure/lib/download.py
seizure/lib/downloadlog.py
seizure/lib/twitch.py
seizure/lib/util.py
seizure/lib/video.py