Metadata-Version: 1.1
Name: seizure
Version: 1.0.4
Summary: Download VODs from Twitch
Home-page: https://github.com/ShaneDrury/seizure
Author: Shane Drury
Author-email: shane.r.drury@gmail.com
License: UNKNOWN
Download-URL: https://github.com/ShaneDrury/seizure/tarball/1.0.4
Keywords: twitch,vod,download
Platform: UNKNOWN
